Workbook

Sheet Painel & Indicadores
B2: 📊 SISTEMA DE GESTÃO DO ALMOXARIFADO - PAINEL GERAL DE CONTROLE
B3: Controle Unificado de Fornecedores, Itens, Movimentações, Cronograma de Entregas e Etiquetas (Sem anexos de arquivos)
B5: FORNECEDORES ATIVOS | C5: =COUNTIF(FORNECEDORES!N4:N100, "Ativo") | E5: TOTAL DE ITENS NO CATÁLOGO | F5: =COUNTA(CADASTRO_ITENS!A4:A100) | H5: VALOR TOTAL EM ESTOQUE | I5: =SUM(CADASTRO_ITENS!M4:M100)
B7: ⚠️ ITENS COM ESTOQUE BAIXO | C7: =COUNTIF(CADASTRO_ITENS!N4:N100, "*BAIXO*") | E7: 🚨 LOTES EM VALIDADE CRÍTICA | F7: =COUNTIF(CONTROLE_VALIDADES!J4:J100, "*CRÍTICO*") + COUNTIF(CONTROLE_VALIDADES!J4:J100, "*VENCIDO*") | H7: 🚚 ENTREGAS AGENDADAS | I7: =COUNTIF(CRONOGRAMA_ENTREGAS!K4:K100, "*Agendada*")
B9: 📌 ESTRUTURA E FUNCIONAMENTO DAS ABAS DO ALMOXARIFADO
B10: 1. FORNECEDORES | C10: Cadastro completo de fornecedores, produtores (PPAIS/PPL/Convencionais), contatos, dados bancários e contratos.
B11: 2. CADASTRO_ITENS | C11: Catálogo de materiais e gêneros alimentícios, unidade de medida, estoques mínimo e cálculo automático do saldo e valor.
B12: 3. MOVIMENTAÇÕES | C12: Livro de registro de Entradas e Saídas diárias, número de NF (sem anexo PDF), lotes, validades e conferente responsável.
B13: 4. CRONOGRAMA_ENTREGAS | C13: Programação de entregas por dia da semana, fornecedor, quantidade prevista versus quantidade recebida e controle de saldos.
B14: 5. IMPRESSÃO_ETIQUETAS | C14: Área formatada pronta para imprimir etiquetas de prateleira, caixas e paletes com código de barras, lote e validade.
B15: 6. CONTROLE_VALIDADES | C15: Rastreabilidade de lotes com cálculo automático de dias restantes para o vencimento e alerta de risco por cores.
B16: 7. INSTRUÇÕES_USO | C16: Manual passo a passo com explicações de fórmulas (PROCV, SOMASE, CONT.SE), atalhos e boas práticas de almoxarifado.

Sheet FORNECEDORES
A1: CADASTRO GERAL DE FORNECEDORES E PRODUTORES (ALMOXARIFADO)
A2: Base de dados oficial para vinculação às entradas, notas fiscais e cronogramas de entrega.
A3: ID FORNECEDOR | B3: RAZÃO SOCIAL / NOME | C3: NOME FANTASIA / PROPRIEDADE | D3: CNPJ / CPF | E3: TIPO FORNECEDOR | F3: RAMO / CATEGORIA | G3: TELEFONE / WHATSAPP | H3: E-MAIL | I3: CIDADE / UF | J3: CONTRATO / ATA RP | K3: VIGÊNCIA ATÉ | L3: DADOS BANCÁRIOS / PIX | M3: DIA HABITUAL DE ENTREGA | N3: STATUS | O3: OBSERVAÇÕES
A4: FORN-001 | B4: COOPERATIVA AGRICOLA FAMILIAR VALE VERDE | C4: COOP VALE VERDE | D4: 12.345.678/0001-90 | E4: PPAIS / Familiar | F4: Hortifrúti & Legumes | G4: (14) 99876-1234 | H4: contato@valeverde.coop.br | I4: Marília/SP | J4: ATA-RP 012/2026 | K4: 31/12/2026 | L4: Banco do Brasil Ag 0123 CC 45678-9 | M4: Terça e Quinta | N4: Ativo | O4: Entrega no período matutino até as 10h
A5: FORN-002 | B5: FRIGORIFICO CENTRAL PAULISTA LTDA | C5: FRIGO CENTRAL | D5: 23.456.789/0001-01 | E5: Convencional | F5: Carnes & Proteínas | G5: (14) 3456-7890 | H5: vendas@frigocentral.com.br | I5: Bauru/SP | J5: CONTRATO 045/2025 | K5: 30/06/2026 | L5: Bradesco Ag 4567 CC 12345-6 | M5: Segunda e Quarta | N5: Ativo | O5: Caminhão refrigerado monitorado
A6: FORN-003 | B6: DISTRIBUIDORA DE ALIMENTOS BOA MESA EIRELI | C6: BOA MESA ALIMENTOS | D6: 34.567.890/0001-12 | E6: Atacadista | F6: Estocáveis & Secos | G6: (11) 3222-4455 | H6: comercial@boamesa.com.br | I6: São Paulo/SP | J6: ATA-RP 008/2026 | K6: 31/12/2026 | L6: Itaú Ag 7890 CC 98765-4 | M6: Sexta-feira | N6: Ativo | O6: Entrega quinzenal de itens secos
A7: FORN-004 | B7: PANIFICADORA E CONFEITARIA ESPERANCA LTDA | C7: PANIF. ESPERANÇA | D7: 45.678.901/0001-23 | E7: Convencional | F7: Panificação & Pães | G7: (14) 98765-4321 | H7: panificadora@esperanca.com | I7: Álvaro de Carvalho/SP | J7: CONTRATO 018/2026 | K7: 31/12/2026 | L7: Caixa Ag 1234 CC 54321-0 | M7: Diário (Seg a Sex) | N7: Ativo | O7: Entrega diária às 06h30
A8: FORN-005 | B8: LATICINIOS COLINA DO SOL INDUSTRIA LTDA | C8: COLINA DO SOL | D8: 56.789.012/0001-34 | E8: Convencional | F8: Laticínios & Derivados | G8: (16) 3344-5566 | H8: pedidos@colinadosol.ind.br | I8: Araraquara/SP | J8: ATA-RP 021/2026 | K8: 31/10/2026 | L8: Santander Ag 3210 CC 65432-1 | M8: Quarta-feira | N8: Ativo | O8: Leite pasteurizado e queijos
A9: FORN-006 | B9: PRODUTOR JOAO BATISTA DA SILVA | C9: SITIO SAO JOSE | D9: 123.456.789-00 | E9: PPL / Familiar | F9: Hortaliças & Frutas | G9: (14) 99123-4567 | H9: joao.sitiosaojose@email.com | I9: Garça/SP | J9: CHAMADA PÚBLICA 002/26 | K9: 31/12/2026 | L9: Banco do Brasil Ag 0890 CC 22114-5 | M9: Terça-feira | N9: Ativo | O9: Alface, couve, cenoura e mandioca
A10: FORN-007 | B10: QUIMICA LIMPA FACIL PRODUTOS DE HIGIENE | C10: LIMPA FACIL | D10: 67.890.123/0001-45 | E10: Convencional | F10: Limpeza & Descartáveis | G10: (11) 4004-9988 | H10: sac@limpafacil.com.br | I10: Campinas/SP | J10: ATA-RP 005/2026 | K10: 31/12/2026 | L10: Banco do Brasil Ag 4321 CC 88776-6 | M10: Última quinta do mês | N10: Ativo | O10: Detergentes, água sanitária e sacos
A11: FORN-008 | B11: M. S. EMBALAGENS E DESCARTAVEIS ME | C11: MS EMBALAGENS | D11: 78.901.234/0001-56 | E11: Convencional | F11: Descartáveis & EPI | G11: (14) 3412-8899 | H11: contato@msembalagens.com.br | I11: Marília/SP | J11: CONTRATO 031/2025 | K11: 15/08/2026 | L11: Bradesco Ag 0099 CC 11223-4 | M11: Quinta-feira | N11: Ativo | O11: Luvas, toucas e potes marmita

Sheet CADASTRO_ITENS
A1: CATÁLOGO DE ITENS E CONTROLE DE ESTOQUE AUTOMATIZADO
A2: Saldos calculados dinamicamente via SOMASE a partir dos registros da aba MOVIMENTAÇÕES.
A3: CÓD. ITEM | B3: CÓD. BARRAS / EAN | C3: DESCRIÇÃO DO ITEM | D3: CATEGORIA | E3: UNID. | F3: LOCALIZAÇÃO / PRATELEIRA | G3: ESTOQUE MÍNIMO | H3: ESTOQUE MÁXIMO | I3: PREÇO UNIT. (R$) | J3: TOTAL ENTRADAS | K3: TOTAL SAÍDAS | L3: SALDO ATUAL | M3: VALOR EM ESTOQUE (R$) | N3: STATUS DO ESTOQUE | O3: FORNECEDOR PADRÃO
A4: IT-001 | B4: 7891000100101 | C4: ARROZ BRANCO TIPO 1 - PCT 5KG | D4: Estocáveis & Secos | E4: PCT | F4: GALPÃO A - CORREDOR 1 - PALETE 01 | G4: 50 | H4: 300 | I4: 24.5 | J4: =SUMIF(MOVIMENTAÇÕES!D:D, A4, MOVIMENTAÇÕES!K:K) | K4: =SUMIF(MOVIMENTAÇÕES!D:D, A4, MOVIMENTAÇÕES!L:L) | L4: =J4-K4 | M4: =L4*I4 | N4: =IF(L4<=0, "🚨 ZERADO", IF(L4<=G4, "⚠️ BAIXO (COMPRAR)", "✅ NORMAL")) | O4: COOP VALE VERDE
A5: IT-002 | B5: 7891000100202 | C5: FEIJAO CARIOCA TIPO 1 - PCT 1KG | D5: Estocáveis & Secos | E5: PCT | F5: GALPÃO A - CORREDOR 1 - PALETE 02 | G5: 40 | H5: 250 | I5: 7.8 | J5: =SUMIF(MOVIMENTAÇÕES!D:D, A5, MOVIMENTAÇÕES!K:K) | K5: =SUMIF(MOVIMENTAÇÕES!D:D, A5, MOVIMENTAÇÕES!L:L) | L5: =J5-K5 | M5: =L5*I5 | N5: =IF(L5<=0, "🚨 ZERADO", IF(L5<=G5, "⚠️ BAIXO (COMPRAR)", "✅ NORMAL")) | O5: DISTRIBUIDORA BOA MESA
A6: IT-003 | B6: 7891000100303 | C6: OLEO DE SOJA REFINADO 900ML | D6: Estocáveis & Secos | E6: UN | F6: GALPÃO A - PRATELEIRA 03 | G6: 60 | H6: 400 | I6: 5.9 | J6: =SUMIF(MOVIMENTAÇÕES!D:D, A6, MOVIMENTAÇÕES!K:K) | K6: =SUMIF(MOVIMENTAÇÕES!D:D, A6, MOVIMENTAÇÕES!L:L) | L6: =J6-K6 | M6: =L6*I6 | N6: =IF(L6<=0, "🚨 ZERADO", IF(L6<=G6, "⚠️ BAIXO (COMPRAR)", "✅ NORMAL")) | O6: DISTRIBUIDORA BOA MESA
A7: IT-004 | B7: 7891000100404 | C7: ACUCAR CRISTAL - PCT 5KG | D7: Estocáveis & Secos | E7: PCT | F7: GALPÃO A - CORREDOR 2 - PALETE 01 | G7: 30 | H7: 200 | I7: 16.2 | J7: =SUMIF(MOVIMENTAÇÕES!D:D, A7, MOVIMENTAÇÕES!K:K) | K7: =SUMIF(MOVIMENTAÇÕES!D:D, A7, MOVIMENTAÇÕES!L:L) | L7: =J7-K7 | M7: =L7*I7 | N7: =IF(L7<=0, "🚨 ZERADO", IF(L7<=G7, "⚠️ BAIXO (COMPRAR)", "✅ NORMAL")) | O7: DISTRIBUIDORA BOA MESA
A8: IT-005 | B8: 7891000100505 | C8: CAFE TORRADO E MOIDO - PCT 500G | D8: Estocáveis & Secos | E8: PCT | F8: GALPÃO A - PRATELEIRA 04 | G8: 40 | H8: 180 | I8: 18.5 | J8: =SUMIF(MOVIMENTAÇÕES!D:D, A8, MOVIMENTAÇÕES!K:K) | K8: =SUMIF(MOVIMENTAÇÕES!D:D, A8, MOVIMENTAÇÕES!L:L) | L8: =J8-K8 | M8: =L8*I8 | N8: =IF(L8<=0, "🚨 ZERADO", IF(L8<=G8, "⚠️ BAIXO (COMPRAR)", "✅ NORMAL")) | O8: DISTRIBUIDORA BOA MESA
A9: IT-006 | B9: 7892000200102 | C9: CARNE BOVINA ACEM RESFRIADO | D9: Carnes & Proteínas | E9: KG | F9: CÂMARA FRIA 01 - CARNES | G9: 80 | H9: 500 | I9: 31.9 | J9: =SUMIF(MOVIMENTAÇÕES!D:D, A9, MOVIMENTAÇÕES!K:K) | K9: =SUMIF(MOVIMENTAÇÕES!D:D, A9, MOVIMENTAÇÕES!L:L) | L9: =J9-K9 | M9: =L9*I9 | N9: =IF(L9<=0, "🚨 ZERADO", IF(L9<=G9, "⚠️ BAIXO (COMPRAR)", "✅ NORMAL")) | O9: FRIGORIFICO CENTRAL PAULISTA
A10: IT-007 | B10: 7892000200203 | C10: PEITO DE FRANGO CONGELADO | D10: Carnes & Proteínas | E10: KG | F10: CÂMARA FRIA 02 - AVES | G10: 100 | H10: 600 | I10: 14.8 | J10: =SUMIF(MOVIMENTAÇÕES!D:D, A10, MOVIMENTAÇÕES!K:K) | K10: =SUMIF(MOVIMENTAÇÕES!D:D, A10, MOVIMENTAÇÕES!L:L) | L10: =J10-K10 | M10: =L10*I10 | N10: =IF(L10<=0, "🚨 ZERADO", IF(L10<=G10, "⚠️ BAIXO (COMPRAR)", "✅ NORMAL")) | O10: FRIGORIFICO CENTRAL PAULISTA
A11: IT-008 | B11: 7892000200304 | C11: SALSICHA RESFRIADA | D11: Carnes & Proteínas | E11: KG | F11: CÂMARA FRIA 01 - CARNES | G11: 30 | H11: 200 | I11: 11.5 | J11: =SUMIF(MOVIMENTAÇÕES!D:D, A11, MOVIMENTAÇÕES!K:K) | K11: =SUMIF(MOVIMENTAÇÕES!D:D, A11, MOVIMENTAÇÕES!L:L) | L11: =J11-K11 | M11: =L11*I11 | N11: =IF(L11<=0, "🚨 ZERADO", IF(L11<=G11, "⚠️ BAIXO (COMPRAR)", "✅ NORMAL")) | O11: FRIGORIFICO CENTRAL PAULISTA
A12: IT-009 | B12: 7893000300103 | C12: ALFACE CRESPA HIGIENIZADA | D12: Hortifrúti & Legumes | E12: KG | F12: CÂMARA DE VERDURAS 03 | G12: 20 | H12: 80 | I12: 6.5 | J12: =SUMIF(MOVIMENTAÇÕES!D:D, A12, MOVIMENTAÇÕES!K:K) | K12: =SUMIF(MOVIMENTAÇÕES!D:D, A12, MOVIMENTAÇÕES!L:L) | L12: =J12-K12 | M12: =L12*I12 | N12: =IF(L12<=0, "🚨 ZERADO", IF(L12<=G12, "⚠️ BAIXO (COMPRAR)", "✅ NORMAL")) | O12: SITIO SAO JOSE - JOAO SILVA
A13: IT-010 | B13: 7893000300204 | C13: TOMATE LONGA VIDA | D13: Hortifrúti & Legumes | E13: KG | F13: CÂMARA DE VERDURAS 03 | G13: 40 | H13: 150 | I13: 7.2 | J13: =SUMIF(MOVIMENTAÇÕES!D:D, A13, MOVIMENTAÇÕES!K:K) | K13: =SUMIF(MOVIMENTAÇÕES!D:D, A13, MOVIMENTAÇÕES!L:L) | L13: =J13-K13 | M13: =L13*I13 | N13: =IF(L13<=0, "🚨 ZERADO", IF(L13<=G13, "⚠️ BAIXO (COMPRAR)", "✅ NORMAL")) | O13: COOP VALE VERDE
A14: IT-011 | B14: 7893000300305 | C14: CENOURA COMUM EXTRA | D14: Hortifrúti & Legumes | E14: KG | F14: CÂMARA DE VERDURAS 03 | G14: 30 | H14: 120 | I14: 4.9 | J14: =SUMIF(MOVIMENTAÇÕES!D:D, A14, MOVIMENTAÇÕES!K:K) | K14: =SUMIF(MOVIMENTAÇÕES!D:D, A14, MOVIMENTAÇÕES!L:L) | L14: =J14-K14 | M14: =L14*I14 | N14: =IF(L14<=0, "🚨 ZERADO", IF(L14<=G14, "⚠️ BAIXO (COMPRAR)", "✅ NORMAL")) | O14: COOP VALE VERDE
A15: IT-012 | B15: 7893000300406 | C15: BATATA INGLESA LAVADA | D15: Hortifrúti & Legumes | E15: KG | F15: GALPÃO B - DEPOSITO SECO | G15: 50 | H15: 250 | I15: 5.4 | J15: =SUMIF(MOVIMENTAÇÕES!D:D, A15, MOVIMENTAÇÕES!K:K) | K15: =SUMIF(MOVIMENTAÇÕES!D:D, A15, MOVIMENTAÇÕES!L:L) | L15: =J15-K15 | M15: =L15*I15 | N15: =IF(L15<=0, "🚨 ZERADO", IF(L15<=G15, "⚠️ BAIXO (COMPRAR)", "✅ NORMAL")) | O15: COOP VALE VERDE
... A21: IT-018 | B21: 7898000800209 | C21: LUVA NITRILICA AZUL TAM G - CX 100 | D21: Descartáveis & EPI | E21: CX | F21: ARMARIO DE EPI 01 | G21: 10 | H21: 50 | I21: 34 | J21: =SUMIF(MOVIMENTAÇÕES!D:D, A21, MOVIMENTAÇÕES!K:K) | K21: =SUMIF(MOVIMENTAÇÕES!D:D, A21, MOVIMENTAÇÕES!L:L) | L21: =J21-K21 | M21: =L21*I21 | N21: =IF(L21<=0, "🚨 ZERADO", IF(L21<=G21, "⚠️ BAIXO (COMPRAR)", "✅ NORMAL")) | O21: MS EMBALAGENS
A22: TOTAL GERAL | J22: =SUM(J4:J21) | K22: =SUM(K4:K21) | L22: =SUM(L4:L21) | M22: =SUM(M4:M21)

Sheet MOVIMENTAÇÕES
A1: LIVRO REGISTRO DE MOVIMENTAÇÕES DE ALMOXARIFADO (ENTRADAS E SAÍDAS)
A2: Registro operacional contínuo. Fórmulas automáticas de descrição e unidade via PROCV. Sem necessidade de anexo PDF de notas fiscais.
A3: ID MOV. | B3: DATA MOV. | C3: TIPO MOVIMENTO | D3: CÓD. ITEM | E3: DESCRIÇÃO DO ITEM | F3: UNID. | G3: Nº NOTA FISCAL / REQ. | H3: FORNECEDOR / DESTINO | I3: Nº DO LOTE | J3: DATA DE VALIDADE | K3: QTD ENTRADA | L3: QTD SAÍDA | M3: PREÇO UNIT. (R$) | N3: VALOR TOTAL (R$) | O3: RESPONSÁVEL / CONFERENTE | P3: OBSERVAÇÕES DO RECEBIMENTO
A4: MOV-0001 | B4: 01/09/2026 | C4: ENTRADA | D4: IT-001 | E4: =IFERROR(VLOOKUP(D4, CADASTRO_ITENS!A:C, 3, FALSE), "") | F4: =IFERROR(VLOOKUP(D4, CADASTRO_ITENS!A:E, 5, FALSE), "") | G4: NF 10452 | H4: COOP VALE VERDE | I4: LOTE-AR26-09 | J4: 01/03/2027 | K4: 150 | L4: 0 | M4: 24.5 | N4: =M4*(K4+L4) | O4: Silva - Almoxarife | P4: Recebido em perfeito estado, sacos limpos e lacrados
A5: MOV-0002 | B5: 01/09/2026 | C5: ENTRADA | D5: IT-002 | E5: =IFERROR(VLOOKUP(D5, CADASTRO_ITENS!A:C, 3, FALSE), "") | F5: =IFERROR(VLOOKUP(D5, CADASTRO_ITENS!A:E, 5, FALSE), "") | G5: NF 10452 | H5: COOP VALE VERDE | I5: LOTE-FE26-08 | J5: 15/02/2027 | K5: 120 | L5: 0 | M5: 7.8 | N5: =M5*(K5+L5) | O5: Silva - Almoxarife | P5: Embalagens a vácuo íntegras
A6: MOV-0003 | B6: 02/09/2026 | C6: ENTRADA | D6: IT-006 | E6: =IFERROR(VLOOKUP(D6, CADASTRO_ITENS!A:C, 3, FALSE), "") | F6: =IFERROR(VLOOKUP(D6, CADASTRO_ITENS!A:E, 5, FALSE), "") | G6: NF 88721 | H6: FRIGORIFICO CENTRAL PAULISTA | I6: LOTE-CAR260902 | J6: 12/09/2026 | K6: 220 | L6: 0 | M6: 31.9 | N6: =M6*(K6+L6) | O6: Fabiano - Nutricionista | P6: Caminhão com temp. a 2.5ºC. SIF verificado
A7: MOV-0004 | B7: 02/09/2026 | C7: ENTRADA | D7: IT-007 | E7: =IFERROR(VLOOKUP(D7, CADASTRO_ITENS!A:C, 3, FALSE), "") | F7: =IFERROR(VLOOKUP(D7, CADASTRO_ITENS!A:E, 5, FALSE), "") | G7: NF 88721 | H7: FRIGORIFICO CENTRAL PAULISTA | I7: LOTE-AVE260901 | J7: 30/11/2026 | K7: 300 | L7: 0 | M7: 14.8 | N7: =M7*(K7+L7) | O7: Fabiano - Nutricionista | P7: Congelado a -14ºC. Embalagem primária intacta
A8: MOV-0005 | B8: 03/09/2026 | C8: ENTRADA | D8: IT-009 | E8: =IFERROR(VLOOKUP(D8, CADASTRO_ITENS!A:C, 3, FALSE), "") | F8: =IFERROR(VLOOKUP(D8, CADASTRO_ITENS!A:E, 5, FALSE), "") | G8: NF 3314 | H8: SITIO SAO JOSE - JOAO SILVA | I8: LOTE-ALF260903 | J8: 08/09/2026 | K8: 45 | L8: 0 | M8: 6.5 | N8: =M8*(K8+L8) | O8: Moutinho - Almoxarifado | P8: Hortaliças frescas recém-colhidas
A9: MOV-0006 | B9: 03/09/2026 | C9: ENTRADA | D9: IT-010 | E9: =IFERROR(VLOOKUP(D9, CADASTRO_ITENS!A:C, 3, FALSE), "") | F9: =IFERROR(VLOOKUP(D9, CADASTRO_ITENS!A:E, 5, FALSE), "") | G9: NF 10488 | H9: COOP VALE VERDE | I9: LOTE-TOM260903 | J9: 15/09/2026 | K9: 90 | L9: 0 | M9: 7.2 | N9: =M9*(K9+L9) | O9: Moutinho - Almoxarifado | P9: Grau de maturação uniforme
A10: MOV-0007 | B10: 04/09/2026 | C10: ENTRADA | D10: IT-014 | E10: =IFERROR(VLOOKUP(D10, CADASTRO_ITENS!A:C, 3, FALSE), "") | F10: =IFERROR(VLOOKUP(D10, CADASTRO_ITENS!A:E, 5, FALSE), "") | G10: NF 55210 | H10: LATICINIOS COLINA DO SOL | I10: LOTE-LEI260830 | J10: 30/12/2026 | K10: 240 | L10: 0 | M10: 4.85 | N10: =M10*(K10+L10) | O10: Silva - Almoxarife | P10: Caixas com 12 unidades
A11: MOV-0008 | B11: 05/09/2026 | C11: ENTRADA | D11: IT-015 | E11: =IFERROR(VLOOKUP(D11, CADASTRO_ITENS!A:C, 3, FALSE), "") | F11: =IFERROR(VLOOKUP(D11, CADASTRO_ITENS!A:E, 5, FALSE), "") | G11: NF 9912 | H11: QUIMICA LIMPA FACIL | I11: LOTE-DET2608 | J11: 01/08/2028 | K11: 30 | L11: 0 | M11: 21 | N11: =M11*(K11+L11) | O11: Costa - Segurança | P11: Galões 5L lacrados com ficha FISPQ
A12: MOV-0009 | B12: 05/09/2026 | C12: ENTRADA | D12: IT-017 | E12: =IFERROR(VLOOKUP(D12, CADASTRO_ITENS!A:C, 3, FALSE), "") | F12: =IFERROR(VLOOKUP(D12, CADASTRO_ITENS!A:E, 5, FALSE), "") | G12: NF 7741 | H12: MS EMBALAGENS | I12: LOTE-MARM2608 | J12: 31/12/2030 | K12: 60 | L12: 0 | M12: 68 | N12: =M12*(K12+L12) | O12: Costa - Segurança | P12: Caixas de 100 unidades cada
A13: MOV-0010 | B13: 08/09/2026 | C13: SAÍDA | D13: IT-001 | E13: =IFERROR(VLOOKUP(D13, CADASTRO_ITENS!A:C, 3, FALSE), "") | F13: =IFERROR(VLOOKUP(D13, CADASTRO_ITENS!A:E, 5, FALSE), "") | G13: REQ-012/26 | H13: Cozinha Central - Almoço | I13: LOTE-AR26-09 | J13: 01/03/2027 | K13: 0 | L13: 25 | M13: 24.5 | N13: =M13*(K13+L13) | O13: Dona Maria - Cozinheira | P13: Requisição diária de preparo do almoço
A14: MOV-0011 | B14: 08/09/2026 | C14: SAÍDA | D14: IT-002 | E14: =IFERROR(VLOOKUP(D14, CADASTRO_ITENS!A:C, 3, FALSE), "") | F14: =IFERROR(VLOOKUP(D14, CADASTRO_ITENS!A:E, 5, FALSE), "") | G14: REQ-012/26 | H14: Cozinha Central - Almoço | I14: LOTE-FE26-08 | J14: 15/02/2027 | K14: 0 | L14: 20 | M14: 7.8 | N14: =M14*(K14+L14) | O14: Dona Maria - Cozinheira | P14: Preparo do feijão diário
A15: MOV-0012 | B15: 08/09/2026 | C15: SAÍDA | D15: IT-006 | E15: =IFERROR(VLOOKUP(D15, CADASTRO_ITENS!A:C, 3, FALSE), "") | F15: =IFERROR(VLOOKUP(D15, CADASTRO_ITENS!A:E, 5, FALSE), "") | G15: REQ-013/26 | H15: Cozinha Central - Almoço | I15: LOTE-CAR260902 | J15: 12/09/2026 | K15: 0 | L15: 60 | M15: 31.9 | N15: =M15*(K15+L15) | O15: Fabiano - Nutricionista | P15: Carne cozida com legumes
... A19: MOV-0016 | B19: 10/09/2026 | C19: SAÍDA | D19: IT-017 | E19: =IFERROR(VLOOKUP(D19, CADASTRO_ITENS!A:C, 3, FALSE), "") | F19: =IFERROR(VLOOKUP(D19, CADASTRO_ITENS!A:E, 5, FALSE), "") | G19: REQ-017/26 | H19: Setor de Montagem de Marmitas | I19: LOTE-MARM2608 | J19: 31/12/2030 | K19: 0 | L19: 10 | M19: 68 | N19: =M19*(K19+L19) | O19: Equipe de Montagem | P19: Fornecimento para montagem diária
A20: TOTAL GERAL | K20: =SUM(K4:K19) | L20: =SUM(L4:L19) | N20: =SUM(N4:N19)

Sheet CRONOGRAMA_ENTREGAS
A1: CRONOGRAMA DE ENTREGAS E RECEBIMENTO DE GÊNEROS (ALMOXARIFADO)
A2: Planejamento de chegadas diárias e semanais para evitar sobrecarga de recebimento e garantir rastreabilidade.
A3: ID AGD. | B3: DATA PREVISTA | C3: DIA SEMANA | D3: TURNO / HORÁRIO | E3: FORNECEDOR | F3: CÓD. ITEM | G3: DESCRIÇÃO DO ITEM | H3: QTD PREVISTA | I3: QTD RECEBIDA | J3: SALDO A RECEBER | K3: STATUS DA ENTREGA | L3: Nº NF RECEBIDA | M3: CONFERENTE RESPONSÁVEL | N3: OBSERVAÇÕES DA CARGA
A4: AGD-001 | B4: 15/09/2026 | C4: Terça-feira | D4: Manhã (07h30 - 09h00) | E4: COOP VALE VERDE | F4: IT-001 | G4: =IFERROR(VLOOKUP(F4, CADASTRO_ITENS!A:C, 3, FALSE), "") | H4: 100 | I4: 100 | J4: =H4-I4 | K4: Entregue Total | L4: NF 10520 | M4: Silva - Almoxarife | N4: Carga conferida e descarregada sem avarias
A5: AGD-002 | B5: 15/09/2026 | C5: Terça-feira | D5: Manhã (09h00 - 10h30) | E5: SITIO SAO JOSE - JOAO SILVA | F5: IT-009 | G5: =IFERROR(VLOOKUP(F5, CADASTRO_ITENS!A:C, 3, FALSE), "") | H5: 30 | I5: 30 | J5: =H5-I5 | K5: Entregue Total | L5: NF 3328 | M5: Moutinho - Almoxarifado | N5: Verduras colhidas pela manhã
A6: AGD-003 | B6: 16/09/2026 | C6: Quarta-feira | D6: Manhã (08h00 - 10h00) | E6: FRIGORIFICO CENTRAL PAULISTA | F6: IT-006 | G6: =IFERROR(VLOOKUP(F6, CADASTRO_ITENS!A:C, 3, FALSE), "") | H6: 150 | I6: 150 | J6: =H6-I6 | K6: Entregue Total | L6: NF 88910 | M6: Fabiano - Nutricionista | N6: Temperatura do caminhão aferida em 3ºC
A7: AGD-004 | B7: 16/09/2026 | C7: Quarta-feira | D7: Tarde (13h30 - 15h00) | E7: LATICINIOS COLINA DO SOL | F7: IT-014 | G7: =IFERROR(VLOOKUP(F7, CADASTRO_ITENS!A:C, 3, FALSE), "") | H7: 180 | I7: 180 | J7: =H7-I7 | K7: Entregue Total | L7: NF 55420 | M7: Silva - Almoxarife | N7: Leite com validade superior a 90 dias
A8: AGD-005 | B8: 21/09/2026 | C8: Segunda-feira | D8: Manhã (07h00 - 08h30) | E8: PANIFICADORA ESPERANCA | F8: IT-013 | G8: =IFERROR(VLOOKUP(F8, CADASTRO_ITENS!A:C, 3, FALSE), "") | H8: 40 | I8: 40 | J8: =H8-I8 | K8: Entregue Total | L8: NF 1205 | M8: Dona Maria - Cozinha | N8: Pães entregues aquecidos e frescos
A9: AGD-006 | B9: 22/09/2026 | C9: Terça-feira | D9: Manhã (08h30 - 10h00) | E9: COOP VALE VERDE | F9: IT-010 | G9: =IFERROR(VLOOKUP(F9, CADASTRO_ITENS!A:C, 3, FALSE), "") | H9: 80 | I9: 0 | J9: =H9-I9 | K9: Agendada | M9: Aguardando | N9: Caminhão com placa prevista ABC-1234
A10: AGD-007 | B10: 23/09/2026 | C10: Quarta-feira | D10: Manhã (08h00 - 10h00) | E10: FRIGORIFICO CENTRAL PAULISTA | F10: IT-007 | G10: =IFERROR(VLOOKUP(F10, CADASTRO_ITENS!A:C, 3, FALSE), "") | H10: 200 | I10: 0 | J10: =H10-I10 | K10: Agendada | M10: Aguardando | N10: Câmara fria 02 higienizada e pronta
A11: AGD-008 | B11: 24/09/2026 | C11: Quinta-feira | D11: Tarde (14h00 - 16h00) | E11: QUIMICA LIMPA FACIL | F11: IT-015 | G11: =IFERROR(VLOOKUP(F11, CADASTRO_ITENS!A:C, 3, FALSE), "") | H11: 20 | I11: 0 | J11: =H11-I11 | K11: Agendada | M11: Aguardando | N11: Descarregamento exclusivo no depósito externo
A12: AGD-009 | B12: 25/09/2026 | C12: Sexta-feira | D12: Manhã (09h00 - 11h00) | E12: DISTRIBUIDORA BOA MESA | F12: IT-003 | G12: =IFERROR(VLOOKUP(F12, CADASTRO_ITENS!A:C, 3, FALSE), "") | H12: 120 | I12: 0 | J12: =H12-I12 | K12: Agendada | M12: Aguardando | N12: Remessa programada de óleo de soja

Sheet IMPRESSÃO_ETIQUETAS
B2: 🏷️ CENTRAL DE IMPRESSÃO DE ETIQUETAS DO ALMOXARIFADO
B3: Como Usar: Digite o Código do Item na célula de controle abaixo para carregar automaticamente ou utilize os modelos pré-configurados prontos para impressão (Ctrl + P).
B4: SELECIONE O CÓDIGO DO ITEM: | C4: IT-001 | E4: DESCRIÇÃO: | F4: =IFERROR(VLOOKUP(C4, CADASTRO_ITENS!A:C, 3, FALSE), "ITEM NÃO ENCONTRADO")
B6: ALMOXARIFADO CENTRAL • CONTROLE DE QUALIDADE | G6: ALMOXARIFADO CENTRAL • CONTROLE DE QUALIDADE
B7: ARROZ BRANCO TIPO 1 - PCT 5KG | G7: FEIJAO CARIOCA TIPO 1 - PCT 1KG
B8: CÓD: IT-001 | D8: UNID: PCT 5KG | G8: CÓD: IT-002 | I8: UNID: PCT 1KG
B9: LOTE: LOTE-AR26-09 | D9: ENTRADA: 01/09/2026 | G9: LOTE: LOTE-FE26-08 | I9: ENTRADA: 01/09/2026
B10: VALIDADE: 01/03/2027 | G10: VALIDADE: 15/02/2027
B11: |||| ||||| |||| |||||||| ||||||| 7891000100101 | G11: |||| ||||| |||| |||||||| ||||||| 7891000100202
B12: FORN: COOP VALE VERDE | CONF: Silva | G12: FORN: COOP VALE VERDE | CONF: Silva
B14: ALMOXARIFADO CENTRAL • CONTROLE DE QUALIDADE | G14: ALMOXARIFADO CENTRAL • CONTROLE DE QUALIDADE
B15: CARNE BOVINA ACEM RESFRIADO | G15: PEITO DE FRANGO CONGELADO
B16: CÓD: IT-006 | D16: UNID: KG | G16: CÓD: IT-007 | I16: UNID: KG
B17: LOTE: LOTE-CAR260902 | D17: ENTRADA: 02/09/2026 | G17: LOTE: LOTE-AVE260901 | I17: ENTRADA: 02/09/2026
B18: VALIDADE: 12/09/2026 | G18: VALIDADE: 30/11/2026
B19: |||| ||||| |||| |||||||| ||||||| 7892000200102 | G19: |||| ||||| |||| |||||||| ||||||| 7892000200203
B20: FORN: FRIGO CENTRAL | CONF: Fabiano | G20: FORN: FRIGO CENTRAL | CONF: Fabiano
B22: ALMOXARIFADO CENTRAL • CONTROLE DE QUALIDADE | G22: ALMOXARIFADO CENTRAL • CONTROLE DE QUALIDADE
B23: LEITE INTEGRAL UHT 1L | G23: DETERGENTE NEUTRO 5L CONCENTRADO
B24: CÓD: IT-014 | D24: UNID: LT | G24: CÓD: IT-015 | I24: UNID: GL 5L
B25: LOTE: LOTE-LEI260830 | D25: ENTRADA: 04/09/2026 | G25: LOTE: LOTE-DET2608 | I25: ENTRADA: 05/09/2026
B26: VALIDADE: 30/12/2026 | G26: VALIDADE: 01/08/2028
B27: |||| ||||| |||| |||||||| ||||||| 7895000500105 | G27: |||| ||||| |||| |||||||| ||||||| 7897000700107
B28: FORN: COLINA DO SOL | CONF: Silva | G28: FORN: LIMPA FACIL | CONF: Costa

Sheet CONTROLE_VALIDADES
A1: PAINEL DE CONTROLE DE VALIDADES E RASTREABILIDADE DE LOTES
A2: Cálculo automático de dias para vencer baseado na data atual. Alertas automáticos para evitar perdas e desperdícios.
A3: CÓD. ITEM | B3: DESCRIÇÃO DO ITEM | C3: Nº DO LOTE | D3: FORNECEDOR | E3: LOCAL DE ARMAZENAGEM | F3: DATA ENTRADA | G3: DATA VALIDADE | H3: QTD DO LOTE | I3: DIAS RESTANTES | J3: CLASSIFICAÇÃO DE RISCO | K3: AÇÃO RECOMENDADA
A4: IT-009 | B4: =IFERROR(VLOOKUP(A4, CADASTRO_ITENS!A:C, 3, FALSE), "") | C4: LOTE-ALF260903 | D4: SITIO SAO JOSE | E4: CÂMARA DE VERDURAS 03 | F4: 03/09/2026 | G4: 28/09/2026 | H4: 30 | I4: =DATEVALUE(G4) - TODAY() | J4: =IF(I4<0, "⛔ VENCIDO", IF(I4<=15, "🚨 CRÍTICO (≤15d)", IF(I4<=30, "⚠️ ALERTA (≤30d)", IF(I4<=60, "🟡 ATENÇÃO (≤60d)", "🟢 OK (REGULAR)")))) | K4: Consumo imediato na salada do almoço
A5: IT-010 | B5: =IFERROR(VLOOKUP(A5, CADASTRO_ITENS!A:C, 3, FALSE), "") | C5: LOTE-TOM260903 | D5: COOP VALE VERDE | E5: CÂMARA DE VERDURAS 03 | F5: 03/09/2026 | G5: 05/10/2026 | H5: 90 | I5: =DATEVALUE(G5) - TODAY() | J5: =IF(I5<0, "⛔ VENCIDO", IF(I5<=15, "🚨 CRÍTICO (≤15d)", IF(I5<=30, "⚠️ ALERTA (≤30d)", IF(I5<=60, "🟡 ATENÇÃO (≤60d)", "🟢 OK (REGULAR)")))) | K5: Distribuir prioritariamente nos próximos 7 dias
A6: IT-006 | B6: =IFERROR(VLOOKUP(A6, CADASTRO_ITENS!A:C, 3, FALSE), "") | C6: LOTE-CAR260902 | D6: FRIGO CENTRAL | E6: CÂMARA FRIA 01 | F6: 02/09/2026 | G6: 10/10/2026 | H6: 160 | I6: =DATEVALUE(G6) - TODAY() | J6: =IF(I6<0, "⛔ VENCIDO", IF(I6<=15, "🚨 CRÍTICO (≤15d)", IF(I6<=30, "⚠️ ALERTA (≤30d)", IF(I6<=60, "🟡 ATENÇÃO (≤60d)", "🟢 OK (REGULAR)")))) | K6: Utilizar no cardápio da semana corrente
A7: IT-007 | B7: =IFERROR(VLOOKUP(A7, CADASTRO_ITENS!A:C, 3, FALSE), "") | C7: LOTE-AVE260901 | D7: FRIGO CENTRAL | E7: CÂMARA FRIA 02 | F7: 02/09/2026 | G7: 30/11/2026 | H7: 300 | I7: =DATEVALUE(G7) - TODAY() | J7: =IF(I7<0, "⛔ VENCIDO", IF(I7<=15, "🚨 CRÍTICO (≤15d)", IF(I7<=30, "⚠️ ALERTA (≤30d)", IF(I7<=60, "🟡 ATENÇÃO (≤60d)", "🟢 OK (REGULAR)")))) | K7: Estoque seguro congelado. Seguir rotação PEPS
A8: IT-014 | B8: =IFERROR(VLOOKUP(A8, CADASTRO_ITENS!A:C, 3, FALSE), "") | C8: LOTE-LEI260830 | D8: COLINA DO SOL | E8: GALPÃO A - PRAT 02 | F8: 04/09/2026 | G8: 30/12/2026 | H8: 200 | I8: =DATEVALUE(G8) - TODAY() | J8: =IF(I8<0, "⛔ VENCIDO", IF(I8<=15, "🚨 CRÍTICO (≤15d)", IF(I8<=30, "⚠️ ALERTA (≤30d)", IF(I8<=60, "🟡 ATENÇÃO (≤60d)", "🟢 OK (REGULAR)")))) | K8: Consumo programado conforme cardápio matutino
A9: IT-002 | B9: =IFERROR(VLOOKUP(A9, CADASTRO_ITENS!A:C, 3, FALSE), "") | C9: LOTE-FE26-08 | D9: COOP VALE VERDE | E9: GALPÃO A - PALETE 02 | F9: 01/09/2026 | G9: 15/02/2027 | H9: 100 | I9: =DATEVALUE(G9) - TODAY() | J9: =IF(I9<0, "⛔ VENCIDO", IF(I9<=15, "🚨 CRÍTICO (≤15d)", IF(I9<=30, "⚠️ ALERTA (≤30d)", IF(I9<=60, "🟡 ATENÇÃO (≤60d)", "🟢 OK (REGULAR)")))) | K9: Gênero seco estocado adequadamente em paletes
A10: IT-001 | B10: =IFERROR(VLOOKUP(A10, CADASTRO_ITENS!A:C, 3, FALSE), "") | C10: LOTE-AR26-09 | D10: COOP VALE VERDE | E10: GALPÃO A - PALETE 01 | F10: 01/09/2026 | G10: 01/03/2027 | H10: 125 | I10: =DATEVALUE(G10) - TODAY() | J10: =IF(I10<0, "⛔ VENCIDO", IF(I10<=15, "🚨 CRÍTICO (≤15d)", IF(I10<=30, "⚠️ ALERTA (≤30d)", IF(I10<=60, "🟡 ATENÇÃO (≤60d)", "🟢 OK (REGULAR)")))) | K10: Gênero seco com amplo prazo de conservação
A11: IT-015 | B11: =IFERROR(VLOOKUP(A11, CADASTRO_ITENS!A:C, 3, FALSE), "") | C11: LOTE-DET2608 | D11: QUIMICA LIMPA FACIL | E11: ALMOXARIFADO LIMPEZA | F11: 05/09/2026 | G11: 01/08/2028 | H11: 25 | I11: =DATEVALUE(G11) - TODAY() | J11: =IF(I11<0, "⛔ VENCIDO", IF(I11<=15, "🚨 CRÍTICO (≤15d)", IF(I11<=30, "⚠️ ALERTA (≤30d)", IF(I11<=60, "🟡 ATENÇÃO (≤60d)", "🟢 OK (REGULAR)")))) | K11: Material de limpeza e saneantes

Sheet INSTRUÇÕES_USO
B2: 📖 MANUAL DE OPERAÇÃO E GUIA DE FUNCIONAMENTO DO ALMOXARIFADO
B4: 1. OBJETIVO DA PLANILHA | C4: Esta planilha foi desenvolvida sob medida para gerenciar todas as operações essenciais do almoxarifado de forma independente no Excel, LibreOffice ou Google Planilhas. Contém fórmulas automáticas para evitar digitação duplicada e simplificar o dia a dia.
B5: 2. CADASTRO DE FORNECEDORES | C5: Aba "FORNECEDORES": Cadastre todos os produtores da agricultura familiar (PPAIS/PPL), atacadistas e distribuidores convencionais com seus respectivos dados bancários, telefones e termos contratuais.
B6: 3. CADASTRO DE ITENS | C6: Aba "CADASTRO_ITENS": Insira o código único do item (ex: IT-001), descrição e ponto de estoque mínimo. Não altere as colunas "Total Entradas", "Total Saídas", "Saldo Atual" e "Status", pois são calculadas automaticamente com a fórmula SOMASE.
B7: 4. LANÇAMENTO DE MOVIMENTAÇÕES | C7: Aba "MOVIMENTAÇÕES": Cada vez que uma mercadoria entrar ou sair, crie uma linha indicando o Tipo (ENTRADA ou SAÍDA) e o Código do Item. A descrição e a unidade de medida são preenchidas automaticamente via PROCV. O número da Nota Fiscal é registrado em campo textual limpo, sem necessidade de carregar anexos em PDF.
B8: 5. CRONOGRAMA DE ENTREGAS | C8: Aba "CRONOGRAMA_ENTREGAS": Utilize esta aba para planejar os dias e horários de chegada de fornecedores. Ao receber a mercadoria, informe a Quantidade Recebida para apurar o saldo restante e atualizar o status.
B9: 6. IMPRESSÃO DE ETIQUETAS | C9: Aba "IMPRESSÃO_ETIQUETAS": Aba configurada para impressão direta em papel A4 comum ou formulário adesivo (Pressione Ctrl + P). Os blocos já contêm layout pronto de rastreabilidade (Item, Lote, Entrada, Validade e Código de Barras).
B10: 7. CONTROLE DE VALIDADES & PEPS | C10: Aba "CONTROLE_VALIDADES": Registre os lotes recebidos para monitorar o prazo de validade em dias com alertas visuais. Pratique sempre a regra PEPS (Primeiro que Entra, Primeiro que Sai) para evitar desperdícios.
B11: 8. SEM ANEXO DE PDF DE NF | C11: Conforme solicitado, o sistema não exige nem contém botões para upload ou anexo de arquivos PDF de notas fiscais, mantendo a planilha leve, rápida e compatível com qualquer computador ou servidor.
